setup.cfg
setup.py
kozh_fig_pac3/__init__.py
kozh_fig_pac3.egg-info/PKG-INFO
kozh_fig_pac3.egg-info/SOURCES.txt
kozh_fig_pac3.egg-info/dependency_links.txt
kozh_fig_pac3.egg-info/not-zip-safe
kozh_fig_pac3.egg-info/top_level.txt
kozh_fig_pac3/circle/__init__.py
kozh_fig_pac3/circle/code.py
kozh_fig_pac3/square/__init__.py
kozh_fig_pac3/square/code.py
kozh_fig_pac3/triangle/__init__.py
kozh_fig_pac3/triangle/code.py