Metadata-Version: 2.1
Name: kozh-fig-pac3
Version: 0.4
Summary: circle, triangle, square
Author-email: alexeykozhakin@gmail.com
